odoo8_addon_l10n_ar_wsfe-8.0.2.0.0.99.dev14-py2.7-nspkg.pth
odoo8_addon_l10n_ar_wsfe-8.0.2.0.0.99.dev14.dist-info/METADATA
odoo8_addon_l10n_ar_wsfe-8.0.2.0.0.99.dev14.dist-info/RECORD
odoo8_addon_l10n_ar_wsfe-8.0.2.0.0.99.dev14.dist-info/WHEEL
odoo8_addon_l10n_ar_wsfe-8.0.2.0.0.99.dev14.dist-info/namespace_packages.txt
odoo8_addon_l10n_ar_wsfe-8.0.2.0.0.99.dev14.dist-info/top_level.txt
odoo_addons/l10n_ar_wsfe/.gitignore
odoo_addons/l10n_ar_wsfe/__init__.py
odoo_addons/l10n_ar_wsfe/__openerp__.py
odoo_addons/l10n_ar_wsfe/account_invoice_view.xml
odoo_addons/l10n_ar_wsfe/account_invoice_workflow.xml
odoo_addons/l10n_ar_wsfe/invoice.py
odoo_addons/l10n_ar_wsfe/wsfe.py
odoo_addons/l10n_ar_wsfe/wsfe_data.xml
odoo_addons/l10n_ar_wsfe/wsfe_demo.xml
odoo_addons/l10n_ar_wsfe/wsfe_request.py
odoo_addons/l10n_ar_wsfe/wsfe_view.xml
odoo_addons/l10n_ar_wsfe/wsfex.py
odoo_addons/l10n_ar_wsfe/report/__init__.py
odoo_addons/l10n_ar_wsfe/report/electronic_invoice_report.xml
odoo_addons/l10n_ar_wsfe/report/invoice_template.odt
odoo_addons/l10n_ar_wsfe/report/parser.py
odoo_addons/l10n_ar_wsfe/security/ir.model.access.csv
odoo_addons/l10n_ar_wsfe/static/description/icon.png
odoo_addons/l10n_ar_wsfe/test/invoice_customer.yml
odoo_addons/l10n_ar_wsfe/test/invoice_massive.yml
odoo_addons/l10n_ar_wsfe/test/invoice_supplier.yml
odoo_addons/l10n_ar_wsfe/test/refund_customer.yml
odoo_addons/l10n_ar_wsfe/tests/__init__.py
odoo_addons/l10n_ar_wsfe/tests/common.py
odoo_addons/l10n_ar_wsfe/tests/test_sinchronize.py
odoo_addons/l10n_ar_wsfe/tests/test_wsfe_basic.py
odoo_addons/l10n_ar_wsfe/wizard/__init__.py
odoo_addons/l10n_ar_wsfe/wizard/wsfe_massive_sinchronize.py
odoo_addons/l10n_ar_wsfe/wizard/wsfe_massive_sinchronize_view.xml
odoo_addons/l10n_ar_wsfe/wizard/wsfe_massive_validation.py
odoo_addons/l10n_ar_wsfe/wizard/wsfe_sinchronize_voucher.py
odoo_addons/l10n_ar_wsfe/wizard/wsfe_sinchronize_voucher_view.xml
odoo_addons/l10n_ar_wsfe/wsfetools/__init__.py
odoo_addons/l10n_ar_wsfe/wsfetools/wsfe_suds.py
odoo_addons/l10n_ar_wsfe/wsfetools/wsfex_suds.py
odoo_addons/l10n_ar_wsfe/wsfetools/test_wsfe/conftest.py
odoo_addons/l10n_ar_wsfe/wsfetools/test_wsfe/test_wsfe.py
odoo_addons/l10n_ar_wsfe/wsfetools/test_wsfe/test_wsfev1.py
