Metadata-Version: 2.1
Name: odoo8-addon-l10n-ar-wsfe
Version: 8.0.2.0.0.99.dev14
Summary: WSFE (Factura Electronica)
Home-page: http://e-mips.com.ar
Author: E-MIPS
Author-email: UNKNOWN
License: GPL-3
Platform: UNKNOWN
Classifier: Programming Language :: Python
Classifier: Framework :: Odoo
Classifier: License :: OSI Approved :: GNU General Public License v3 (GPLv3)
Requires-Python: ~=2.7
Requires-Dist: odoo8-addon-base-vat-ar
Requires-Dist: odoo8-addon-l10n-ar-point-of-sale
Requires-Dist: odoo8-addon-l10n-ar-wsaa
Requires-Dist: odoo (<9.0a,>=8.0a)
